sugaku/__init__.py
Sugaku-0.1.2.dist-info/METADATA
Sugaku-0.1.2.dist-info/WHEEL
Sugaku-0.1.2.dist-info/top_level.txt
Sugaku-0.1.2.dist-info/RECORD
