Metadata-Version: 2.1
Name: Sugaku
Version: 0.1.2
Summary: Python module to generate a calculation chain.
Home-page: UNKNOWN
Author: ZeyaTsu
Author-email: zeyatsou@gmail.com
License: UNKNOWN
Keywords: python,math,mathematics,maths,calculus,calculations
Platform: UNKNOWN
Classifier: Development Status :: 5 - Production/Stable
Classifier: Intended Audience :: Developers
Classifier: Programming Language :: Python :: 3
Classifier: Operating System :: Unix
Classifier: Operating System :: MacOS :: MacOS X
Classifier: Operating System :: Microsoft :: Windows
